{
  "version": 1,
  "generated_at": "2026-05-01T06:27:27Z",
  "context_path": ".wiki/roadmap/tasks/TASK-002/context.json",
  "budget": {
    "target_tokens": 6000,
    "policy": "Use this packet first. Expand only listed specs/code/evidence when phase or stale revision requires exact source."
  },
  "task": {
    "id": "TASK-002",
    "title": "Map code ownership into spec hierarchy",
    "status": "done",
    "phase": "done",
    "priority": "high",
    "kind": "architecture",
    "summary": "Refine the inferred boundary docs until wiki/system mirrors the repo's real ownership seams without creating doc sprawl.",
    "labels": [
      "brownfield",
      "mapping"
    ],
    "goal": {
      "outcome": "wiki/system reflects real stable ownership seams in the repo.",
      "acceptance": [
        "Each meaningful code area maps to one canonical owning spec.",
        "Unnecessary inferred boundaries are removed or collapsed."
      ],
      "non_goals": [
        "Create a spec for every folder regardless of architectural value."
      ],
      "verification": [
        "Review inferred boundary docs against actual repo structure.",
        "Run rebuild and inspect mapping/drift output."
      ]
    },
    "delta": {
      "desired": "Each meaningful layer or component has one canonical owning spec.",
      "current": "Setup can infer first-pass boundaries, but humans still need to confirm or reshape them.",
      "closure": "Add, remove, or rewrite inferred spec folders until they match real stable ownership seams."
    }
  },
  "revision": {
    "task": {
      "digest": "ce7cf418f288fc3ba4a317fbe1442130ca0a995e06499eb096279d3995ff8f85"
    },
    "git": {
      "head": "a6fc64223df319b53cd863958c062c28180ebbd8",
      "dirty": true,
      "dirty_paths": [
        ".wiki/knowledge/system/overview.md",
        ".wiki/roadmap.json",
        "extensions/codewiki/contracts.ts",
        "extensions/codewiki/index.ts",
        "scripts/smoke-test.mjs"
      ],
      "paths": {
        ".wiki/knowledge/system/extensions/codewiki/overview.md": "a6fc64223df3",
        ".wiki/knowledge/system/overview.md": "a6fc64223df3",
        ".wiki/roadmap.json": "a6fc64223df3",
        "extensions/codewiki": "a6fc64223df3",
        "scripts/smoke-test.mjs": "a6fc64223df3",
        "skills": "a6fc64223df3"
      }
    },
    "spec_digest": "9df4d8f85ae4190596779e6fbb2e4567236d0377a5bb7996576861e323300525",
    "code_digest": "aec85516d5edcbce8736413e6b9eeff7a5f55e9655ab2c0ba89a532b028016e3",
    "graph": {
      "git": {
        "head": "a6fc64223df319b53cd863958c062c28180ebbd8",
        "dirty": true
      },
      "spec_digest": "755fe900c93b1f0937e01d7b455e1e15a1d92846006b1f96d9561c9542175e3f",
      "task_digest": "804f3ab22cad6fffcb05736fa39d0ca59d5fe35cd02aeed436dab4407d09130d",
      "evidence_digest": "4e3c6700498f6c1597ab67de41b61627b1e276b937c410e4e8d2949071a101b2"
    }
  },
  "specs": [
    {
      "path": ".wiki/knowledge/system/overview.md",
      "title": "System Overview",
      "summary": "Main runtime areas and ownership boundaries for codewiki.",
      "state": "active",
      "owners": [
        "architecture"
      ],
      "code_paths": [
        "extensions/codewiki",
        "scripts/rebuild_docs_meta.py",
        "skills"
      ],
      "revision": {
        "digest": "39ad3012eefb6a09ae5424f3fdcbd06e7acc1a471d97e20004d4a9c65be4f1c8"
      },
      "expand": {
        "read": ".wiki/knowledge/system/overview.md"
      }
    },
    {
      "path": ".wiki/knowledge/system/extensions/codewiki/overview.md",
      "title": "Extensions / Codewiki",
      "summary": "Pi package resources, extension commands/tools, packaged skills, status UI, and generated wiki templates for codewiki.",
      "state": "active",
      "owners": [
        "engineering"
      ],
      "code_paths": [
        "extensions/codewiki",
        "skills",
        "scripts/smoke-test.mjs"
      ],
      "revision": {
        "digest": "8e198fb5f2332459640a7cf09067f99a6a7f2e09eacb5e9dcee82dfd3bbe5605"
      },
      "expand": {
        "read": ".wiki/knowledge/system/extensions/codewiki/overview.md"
      }
    }
  ],
  "code": {
    "paths": [
      "extensions/codewiki",
      "skills",
      "scripts/smoke-test.mjs"
    ],
    "digest": "aec85516d5edcbce8736413e6b9eeff7a5f55e9655ab2c0ba89a532b028016e3",
    "expand": [
      {
        "read": "extensions/codewiki"
      },
      {
        "read": "skills"
      },
      {
        "read": "scripts/smoke-test.mjs"
      }
    ]
  },
  "evidence": {
    "verdict": "pass",
    "summary": "Mapped real package ownership seams into system specs: extension/package surface owns commands, tools, status UI, packaged skills, bootstrap templates, smoke tests, and root discovery; runtime policy owns transaction/verifier/capability boundary.",
    "checks_run": [
      "npm run typecheck -- --pretty false",
      "npm test",
      "codewiki_state refresh"
    ],
    "files_touched": [
      ".wiki/knowledge/system/overview.md",
      ".wiki/knowledge/system/extensions/codewiki/overview.md"
    ],
    "issues": [],
    "updated_at": "2026-05-01T03:11:02Z"
  },
  "expansion": {
    "task_json": ".wiki/roadmap/tasks/TASK-002/task.json",
    "roadmap_state": ".wiki/roadmap-state.json",
    "status_state": ".wiki/status-state.json",
    "graph": ".wiki/graph.json"
  }
}
